gogogate2_api/__init__.py
gogogate2_api/cli.py
gogogate2_api/common.py
gogogate2_api/const.py
gogogate2_api-3.0.1.dist-info/LICENSE
gogogate2_api-3.0.1.dist-info/METADATA
gogogate2_api-3.0.1.dist-info/WHEEL
gogogate2_api-3.0.1.dist-info/entry_points.txt
gogogate2_api-3.0.1.dist-info/RECORD
