Metadata-Version: 2.1
Name: gogogate2-api
Version: 3.0.1
Summary: Library for connecting to GogoGate2 and iSmartGate hubs
Home-page: https://github.com/vangorra/python_gogogate2_api
License: MIT
Keywords: gogogate2,ismartgate,api
Author: Robbie Van Gorkom
Author-email: robbie.van.gorkom@protonmail.com
Requires-Python: >=3.8.1,<4
Classifier: License :: OSI Approved :: MIT License
Classifier: Programming Language :: Python :: 3
Classifier: Programming Language :: Python :: 3.9
Classifier: Programming Language :: Python :: 3.10
Classifier: Programming Language :: Python :: 3.11
Requires-Dist: click (>=7.1.2)
Requires-Dist: defusedxml (>=0.6.0)
Requires-Dist: httpx (>=0.16.1)
Requires-Dist: pycryptodome (>=3.9.7)
Requires-Dist: requests (>=2.23.0)
Requires-Dist: typing-extensions (>=3.7.4.2)
Project-URL: Repository, https://github.com/vangorra/python_gogogate2_api
